Workbook

Sheet INGRESOS (2)
A1: Nº | B1: FECHA | C1: NOMBRE | D1: CARRO | E1: SILENCIADOR | F1: CAUCHERA | G1: ALINEACION | H1: ELECTRONICA | I1: MECANICA | J1: FRENO | K1: LAVADO | L1: REPUESTO | M1: TOTAL | N1: CONTADO | O1: POR COBRAR | P1: CASHEA | Q1: IVA | R1: INICIAL | S1: FINANCIADO | T1: TASA | U1: PAGO MOVIL EXTERIOR | V1: PAGO MOVIL BANESCO | W1: PUNTO BANCAMIGA | X1: PUNTO BANESCO | Y1: PUNTO BANESCO | Z1: BNC | AA1: $ | AB1: BINANCE | AC1: ZELLE
A2: =ROW()-1 -> 1 | B2: 46063 | C2: DANIELA MARTINEZ | D2: HONDA | E2: 70 | F2: 10 | G2: 15 | M2: ='INGRESOS (2)'!$E2+'INGRESOS (2)'!$F2+'INGRESOS (2)'!$G2+'INGRESOS (2)'!$I2+'INGRESOS (2)'!$J2+'INGRESOS (2)'!$K2+'INGRESOS (2)'!$L2+'INGRESOS (2)'!$H2+'INGRESOS (2)'!#REF! -> #REF! | N2: 95 | Q2: ='INGRESOS (2)'!$P2*16% -> 0 | S2: ='INGRESOS (2)'!$P2+'INGRESOS (2)'!$Q2+-'INGRESOS (2)'!$R2 -> 0 | T2: 451.5 | U2: ='INGRESOS (2)'!$N2*'INGRESOS (2)'!$T2 -> 42892.5
A3: =ROW()-1 -> 2 | B3: 46091 | C3: DANIELA MARTINEZ | D3: HONDA | E3: 50 | I3: 120 | M3: ='INGRESOS (2)'!$E3+'INGRESOS (2)'!$F3+'INGRESOS (2)'!$G3+'INGRESOS (2)'!$I3+'INGRESOS (2)'!$J3+'INGRESOS (2)'!$K3+'INGRESOS (2)'!$L3+'INGRESOS (2)'!$H3+'INGRESOS (2)'!#REF! -> #REF! | O3: ='INGRESOS (2)'!$M3 -> #REF! | Q3: ='INGRESOS (2)'!$P3*16% -> 0 | S3: ='INGRESOS (2)'!$P3+'INGRESOS (2)'!$Q3+-'INGRESOS (2)'!$R3 -> 0
A4: =ROW()-1 -> 3 | B4: 46091 | C4: ANDREA BELLO | D4: MAZDA | E4: 20 | F4: 20 | M4: ='INGRESOS (2)'!$E4+'INGRESOS (2)'!$F4+'INGRESOS (2)'!$G4+'INGRESOS (2)'!$I4+'INGRESOS (2)'!$J4+'INGRESOS (2)'!$K4+'INGRESOS (2)'!$L4+'INGRESOS (2)'!$H4+'INGRESOS (2)'!#REF! -> #REF! | P4: ='INGRESOS (2)'!$M4 -> #REF! | Q4: ='INGRESOS (2)'!$P4*16% -> #REF! | R4: 20 | S4: ='INGRESOS (2)'!$P4+'INGRESOS (2)'!$Q4+-'INGRESOS (2)'!$R4 -> #REF! | T4: 460 | X4: ='INGRESOS (2)'!$R4*'INGRESOS (2)'!$T4 -> 9200
A5: Total | E5: =SUBTOTAL(109,'INGRESOS (2)'!$E$2:$E$4) -> 140 | F5: =SUBTOTAL(109,'INGRESOS (2)'!$F$2:$F$4) -> 30 | G5: =SUBTOTAL(109,'INGRESOS (2)'!$G$2:$G$4) -> 15 | H5: =SUBTOTAL(109,'INGRESOS (2)'!$H$2:$H$4) -> 0 | I5: =SUBTOTAL(109,'INGRESOS (2)'!$I$2:$I$4) -> 120 | J5: =SUBTOTAL(109,'INGRESOS (2)'!$J$2:$J$4) -> 0 | K5: =SUBTOTAL(109,'INGRESOS (2)'!$K$2:$K$4) -> 0 | L5: =SUBTOTAL(109,'INGRESOS (2)'!$L$2:$L$4) -> 0 | M5: =SUBTOTAL(109,'INGRESOS (2)'!$M$2:$M$4) -> #REF! | N5: =SUBTOTAL(109,'INGRESOS (2)'!$N$2:$N$4) -> 95 | O5: =SUBTOTAL(109,'INGRESOS (2)'!$O$2:$O$4) -> #REF! | P5: =SUBTOTAL(109,'INGRESOS (2)'!$P$2:$P$4) -> #REF! | Q5: =SUBTOTAL(109,'INGRESOS (2)'!$Q$2:$Q$4) -> #REF! | R5: =SUBTOTAL(109,'INGRESOS (2)'!$R$2:$R$4) -> 20 | S5: =SUBTOTAL(109,'INGRESOS (2)'!$S$2:$S$4) -> #REF! | U5: =SUBTOTAL(109,'INGRESOS (2)'!$U$2:$U$4) -> 42892.5 | V5: =SUBTOTAL(109,'INGRESOS (2)'!$V$2:$V$4) -> 0 | W5: =SUBTOTAL(109,'INGRESOS (2)'!$W$2:$W$4) -> 0 | X5: =SUBTOTAL(109,'INGRESOS (2)'!$X$2:$X$4) -> 9200 | Y5: =SUBTOTAL(109,'INGRESOS (2)'!$Y$2:$Y$4) -> 0 | Z5: =SUBTOTAL(109,'INGRESOS (2)'!$Z$2:$Z$4) -> 0 | AA5: =SUBTOTAL(109,'INGRESOS (2)'!$AA$2:$AA$4) -> 0 | AB5: =SUBTOTAL(109,'INGRESOS (2)'!$AB$2:$AB$4) -> 0 | AC5: =SUBTOTAL(109,'INGRESOS (2)'!$AC$2:$AC$4) -> 0
R7: SALDOS
B8: LEYENDA | C8: CANTIDAD | D8: MONTO | F8: METODO DE PAGO | G8: CANTIDAD | H8: MONTO | J8: FORMA DE PAGO | K8: CANTIDAD | L8: MONTO | M8: TASA | N8: $ | R8: BANCO | S8: BS | T8: BS | U8: $
B9: CLIENTES ATENDIDOS | C9: =SUBTOTAL(102, B1:B4) -> 3 | F9: CASHEA | G9: =SUBTOTAL(102, 'INGRESOS (2)'!$P$1:$P$5) -> 0 | H9: ='INGRESOS (2)'!$P$5 -> #REF! | J9: PM BANESCO | K9: =SUBTOTAL(102, 'INGRESOS (2)'!$V$1:$V$5) -> 0 | L9: ='INGRESOS (2)'!$X$5 -> 9200 | M9: 102.3 | N9: =Tabla511172329354147535965727951219263442516069859610511412316[[#This Row],[MONTO ]]/Tabla511172329354147535965727951219263442516069859610511412316[[#This Row],[TASA ]] -> 89.931574 | R9: BNC
B10: SILENCIADORES | C10: =SUBTOTAL(102, E1:E4) -> 3 | D10: ='INGRESOS (2)'!$E$5 -> 140 | F10: CONTADO | G10: =SUBTOTAL(102, 'INGRESOS (2)'!$N$1:$N$5) -> 1 | H10: ='INGRESOS (2)'!$N$5 -> 95 | J10: PM EXTERIOR | K10: =SUBTOTAL(102, 'INGRESOS (2)'!$U$1:$U$5) -> 1 | L10: ='INGRESOS (2)'!$U$5 -> 42892.5 | N10: =Tabla511172329354147535965727951219263442516069859610511412316[[#This Row],[MONTO ]]/Tabla511172329354147535965727951219263442516069859610511412316[[#This Row],[TASA ]] -> #DIV/0! | R10: BANESCO | T10: =Tabla68758281522293745546372889910811712619[[#This Row],[BS]]/Tabla511172329354147535965727951219263442516069859610511412316[[#This Row],[TASA ]] -> #DIV/0!
B11: CAUCHERA | C11: =SUBTOTAL(102, 'INGRESOS (2)'!$F$1:$F$5) -> 2 | D11: ='INGRESOS (2)'!$F$5 -> 30 | F11: POR COBRAR | G11: =SUBTOTAL(102, 'INGRESOS (2)'!$O$1:$O$5) -> 0 | H11: ='INGRESOS (2)'!$O$5 -> #REF! | J11: P. BANESCO | K11: =SUBTOTAL(102, 'INGRESOS (2)'!$X$1:$X$5) -> 1 | L11: ='INGRESOS (2)'!$Y$5 -> 0 | N11: =Tabla511172329354147535965727951219263442516069859610511412316[[#This Row],[MONTO ]]/Tabla511172329354147535965727951219263442516069859610511412316[[#This Row],[TASA ]] -> #DIV/0! | R11: EXTERIOR | T11: =Tabla68758281522293745546372889910811712619[[#This Row],[BS]]/Tabla511172329354147535965727951219263442516069859610511412316[[#This Row],[TASA ]] -> #DIV/0!
B12: ALINEACION | C12: =SUBTOTAL(102, 'INGRESOS (2)'!$G$1:$G$5) -> 1 | D12: ='INGRESOS (2)'!$G$5 -> 15 | F12: Total | G12: =SUM(G9:G11) -> 1 | H12: =SUBTOTAL(109,'INGRESOS (2)'!$H$9:$H$11) -> #REF! | J12: P. BANCAMIGA | K12: =SUBTOTAL(102,'INGRESOS (2)'!$W$1:$W$5) -> 0 | L12: ='INGRESOS (2)'!$W$5 -> 0 | N12: =Tabla511172329354147535965727951219263442516069859610511412316[[#This Row],[MONTO ]]/Tabla511172329354147535965727951219263442516069859610511412316[[#This Row],[TASA ]] -> #DIV/0! | R12: BANCAMIGA | T12: =Tabla68758281522293745546372889910811712619[[#This Row],[BS]]/Tabla511172329354147535965727951219263442516069859610511412316[[#This Row],[TASA ]] -> #DIV/0!
B13: ELECTRONICA | C13: =SUBTOTAL(102, 'INGRESOS (2)'!$H$1:$H$5) -> 0 | D13: ='INGRESOS (2)'!$H$5 -> 0 | J13: BNC | K13: =SUBTOTAL(102, 'INGRESOS (2)'!$Z$1:$Z$5) -> 0 | L13: ='INGRESOS (2)'!$Z$5 -> 0 | R13: EFECTIVO | T13: =Tabla68758281522293745546372889910811712619[[#This Row],[BS]]/Tabla511172329354147535965727951219263442516069859610511412316[[#This Row],[TASA ]] -> #DIV/0!
B14: MECANICA | C14: =SUBTOTAL(102, 'INGRESOS (2)'!$I$1:$I$5) -> 1 | D14: ='INGRESOS (2)'!$I$5 -> 120 | F14: FACTURAS | G14: MONTOS | J14: DIVISAS | K14: =SUBTOTAL(102, 'INGRESOS (2)'!$V$1:$V$5) -> 0 | N14: ='INGRESOS (2)'!$AA$5 -> 0 | R14: BINANCE | T14: =Tabla68758281522293745546372889910811712619[[#This Row],[BS]]/Tabla511172329354147535965727951219263442516069859610511412316[[#This Row],[TASA ]] -> #DIV/0!
B15: FRENO | C15: =SUBTOTAL(102,'INGRESOS (2)'!$J$1:$J$5) -> 0 | D15: ='INGRESOS (2)'!$J$5 -> 0 | F15: BI | G15: ='INGRESOS (2)'!$P$5 -> #REF! | J15: BINANCE | K15: =SUBTOTAL(102, 'INGRESOS (2)'!$AB$1:$AB$5) -> 0 | N15: ='INGRESOS (2)'!$AB$5 -> 0 | R15: ZELLE | T15: =Tabla68758281522293745546372889910811712619[[#This Row],[BS]]/Tabla511172329354147535965727951219263442516069859610511412316[[#This Row],[TASA ]] -> #DIV/0!
B16: LAVADO | C16: =SUBTOTAL(102, 'INGRESOS (2)'!$K$1:$K$5) -> 0 | D16: ='INGRESOS (2)'!$K$5 -> 0 | F16: IVA | G16: ='INGRESOS (2)'!$Q$5 -> #REF! | J16: ZELLE | K16: =SUBTOTAL(102,'INGRESOS (2)'!$AC$1:$AC$5) -> 0 | N16: ='INGRESOS (2)'!$AC$5 -> 0 | R16: Total | S16: =SUBTOTAL(109,Tabla68758281522293745546372889910811712619[BS]) -> 0 | T16: =SUBTOTAL(109,Tabla68758281522293745546372889910811712619[[BS ]]) -> #DIV/0!
B17: REPUESTO | C17: =SUBTOTAL(102, 'INGRESOS (2)'!$L$1:$L$5) -> 0 | D17: ='INGRESOS (2)'!$L$5 -> 0 | F17: Total | G17: =SUBTOTAL(109,'INGRESOS (2)'!$G$15:$G$16) -> #REF! | J17: Total | K17: =SUBTOTAL(109,Tabla511172329354147535965727951219263442516069859610511412316[[CANTIDAD ]]) -> 0 | L17: =SUBTOTAL(109,Tabla511172329354147535965727951219263442516069859610511412316[[MONTO ]]) -> 52092.5 | N17: =SUBTOTAL(109,Tabla511172329354147535965727951219263442516069859610511412316[$ ]) -> #DIV/0!
B18: Total | D18: =SUBTOTAL(109,Tabla39152127333945515763707731017243240495867839410311212114[[MONTO ]]) -> 305 | J18: PM BANESCO | K18: PAGO MOVIL BANESCO
F19: CASHEA | G19: MONTOS | J19: PM EXTERIOR | K19: PAGO MOVIL EXTERIOR
F20: INICIAL | G20: ='INGRESOS (2)'!$R$5 -> 20 | J20: P. BANCAMIGA | K20: PUNTO PBANCAMIGA
F21: FINANCIADO | G21: ='INGRESOS (2)'!$S$5 -> #REF! | J21: P. BANESCO | K21: PUNTO BANESCO
F22: Total | G22: =SUBTOTAL(109,Tabla713192531374349556167748171421283644536271879810711612518[[MONTOS ]]) -> #REF!
B30: SEGUIDORES INSTAGRAM | D30: REGRISTRO EN LA APP | F30: RCV | H30: CERTIFICADO MEDICO
B31: INICIAL | C31: 2368 | D31: INICIAL | E31: 488 | F31: INICIAL | G31: 0 | H31: INICIAL | I31: 2 | K31: CLIENTES EN BASE DE DATOS | M31: 5
B32: TOTAL | C32: =C31+#REF! -> #REF! | E32: =E31+#REF! -> #REF! | G32: 0 | I32: =SUM(I31:I31) -> 2
B37: PRODUCTO | C37: CANTIDAD
B38: FLEXIBLE | C38: 0 | F38: CARROS EN TALLER | H38: MEANICO | I38: TRABAJO
B39: RESONADOR | C39: 1 | F39: AIDA CHEROKEE
B40: CLH 60 | C40: 0 | F40: GUTIERREZ FORTALEZA
B41: CLH 40 | C41: 2
B42: CLH 30 | C42: 1
B43: GOMAS | C43: 0
B44: TUBERIA | C44: 1
B45: GOMAS | C45: 0
B46: COLA CROMADA | C46: 1
